unique_names_generator/__init__.py
unique_names_generator/generator.py
unique_names_generator/data/__init__.py
unique_names_generator/data/adjectives.py
unique_names_generator/data/animals.py
unique_names_generator/data/colors.py
unique_names_generator/data/countries.py
unique_names_generator/data/languages.py
unique_names_generator/data/names.py
unique_names_generator/data/star_wars.py
unique_names_generator-1.0.2.dist-info/LICENSE
unique_names_generator-1.0.2.dist-info/METADATA
unique_names_generator-1.0.2.dist-info/WHEEL
unique_names_generator-1.0.2.dist-info/top_level.txt
unique_names_generator-1.0.2.dist-info/RECORD
