Metadata-Version: 2.1
Name: unique-names-generator
Version: 1.0.2
Summary: Generate unique and memorable name strings.
Home-page: https://github.com/ravi-ojha/py-unique-names-generator
Author: Ravi Ojha
Author-email: ivarojha@gmail.com
License: MIT
Platform: UNKNOWN
Classifier: License :: OSI Approved :: MIT License
Classifier: Programming Language :: Python
Classifier: Programming Language :: Python :: 3
Classifier: Programming Language :: Python :: 3.6
Classifier: Programming Language :: Python :: 3.7
Classifier: Programming Language :: Python :: 3.8
Classifier: Programming Language :: Python :: Implementation :: CPython
Classifier: Programming Language :: Python :: Implementation :: PyPy
Requires-Python: >=3.6.0
Provides-Extra: dev
License-File: LICENSE
